galaxy/__init__.py
galaxy/py.typed
galaxy/schema/__init__.py
galaxy/schema/fetch_data.py
galaxy/schema/fields.py
galaxy/schema/generics.py
galaxy/schema/groups.py
galaxy/schema/help.py
galaxy/schema/history.py
galaxy/schema/invocation.py
galaxy/schema/item_tags.py
galaxy/schema/jobs.py
galaxy/schema/library_contents.py
galaxy/schema/notifications.py
galaxy/schema/remote_files.py
galaxy/schema/schema.py
galaxy/schema/storage_cleaner.py
galaxy/schema/tasks.py
galaxy/schema/types.py
galaxy/schema/visualization.py
galaxy/schema/workflows.py
galaxy/schema/bco/__init__.py
galaxy/schema/bco/description_domain.py
galaxy/schema/bco/error_domain.py
galaxy/schema/bco/execution_domain.py
galaxy/schema/bco/io_domain.py
galaxy/schema/bco/parametric_domain.py
galaxy/schema/bco/provenance_domain.py
galaxy/schema/bco/usability_domain.py
galaxy/schema/bco/util.py
galaxy/schema/drs/__init__.py
galaxy/schema/workflow/__init__.py
galaxy/schema/workflow/comments.py
galaxy_schema-25.0.3.dist-info/licenses/LICENSE
galaxy_schema-25.0.3.dist-info/METADATA
galaxy_schema-25.0.3.dist-info/WHEEL
galaxy_schema-25.0.3.dist-info/top_level.txt
galaxy_schema-25.0.3.dist-info/RECORD
